django_arduino_controller/BaseApp.py
django_arduino_controller/__init__.py
django_arduino_controller/admin.py
django_arduino_controller/apps.py
django_arduino_controller/consumers.py
django_arduino_controller/models.py
django_arduino_controller/routing.py
django_arduino_controller/tests.py
django_arduino_controller/urls.py
django_arduino_controller/views.py
django_arduino_controller/migrations/__init__.py
django_arduino_controller/static/django_arduino_controller/api_programmer.js
django_arduino_controller/static/django_arduino_controller/arduino_api_controller.css
django_arduino_controller/static/django_arduino_controller/arduino_api_controller.js
django_arduino_controller/static/django_arduino_controller/arduino_api_programmer.css
django_arduino_controller/static/django_arduino_controller/django_arduino_controller.js
django_arduino_controller/static/django_arduino_controller/json_websocket.js
django_arduino_controller/templates/api_controller_sidebar.html
django_arduino_controller/templates/api_programmer.html
django_arduino_controller/templates/django_arduino_controller_index.html
django_arduino_controller/templates/django_arduino_controller_logger.html
django_arduino_controller/templates/logger_frame.html
django_arduino_controller-0.1.1566484023.dist-info/LICENSE.txt
django_arduino_controller-0.1.1566484023.dist-info/METADATA
django_arduino_controller-0.1.1566484023.dist-info/WHEEL
django_arduino_controller-0.1.1566484023.dist-info/top_level.txt
django_arduino_controller-0.1.1566484023.dist-info/RECORD
